mylibpy2/__init__.py
mylibpy2/aes.py
mylibpy2/codec_util.py
mylibpy2/crypto_util.py
mylibpy2/datetime_.py
mylibpy2/datetime_util.py
mylibpy2/http_util.py
mylibpy2/logger.py
mylibpy2-0.4.0.dist-info/METADATA
mylibpy2-0.4.0.dist-info/RECORD
mylibpy2-0.4.0.dist-info/WHEEL
mylibpy2-0.4.0.dist-info/entry_points.txt
mylibpy2-0.4.0.dist-info/top_level.txt
