Metadata-Version: 2.1
Name: mylibpy2
Version: 0.4.0
Summary: A simple polyglot libraries
Home-page: UNKNOWN
Author: Wonho Jang
Author-email: jwh1807@gmail.com
License: MIT
Platform: UNKNOWN
Classifier: Development Status :: 3 - Alpha
Classifier: Intended Audience :: Developers
Classifier: Topic :: Software Development :: Libraries :: Python Modules
Classifier: License :: OSI Approved :: MIT License
Classifier: Programming Language :: Python :: 2.7
Requires-Python: >=2.7, <3
Requires-Dist: pyaes (==1.6.1)
Requires-Dist: chardet (==3.0.4)
Requires-Dist: beautifulsoup4 (==4.6.0)
Requires-Dist: requests (==2.18.4)
Provides-Extra: test
Requires-Dist: responses (==0.8.1); extra == 'test'
